e2w/__init__.py
e2w/e2w.py
e2w/styles/__init__.py
e2w/styles/font_family.py
e2w/styles/page_layout.py
e2w/styles/table_style.py
e2w-0.1.3.dist-info/licenses/LICENSE
static/img/logo.jpg
static/img/product.png
static/img/table.png
templates/sample.template
e2w-0.1.3.dist-info/METADATA
e2w-0.1.3.dist-info/WHEEL
e2w-0.1.3.dist-info/top_level.txt
e2w-0.1.3.dist-info/RECORD
