Metadata-Version: 2.4
Name: e2w
Version: 0.1.3
Summary: Support exporting template with HTML tag to Word file
Author-email: Alan <mr.ngtruong@gmail.com>
License: MIT License
Project-URL: Homepage, https://github.com/rethat/e2w
Project-URL: Bug Tracker, https://github.com/rethat/e2w/issues
Requires-Python: >=3.9
License-File: LICENSE
Requires-Dist: requests
Requires-Dist: lxml
Requires-Dist: pandas
Requires-Dist: python-docx
Requires-Dist: beautifulsoup4
Dynamic: license-file
